bertsenclu/__init__.py
bertsenclu/senClu.py
bertsenclu/visUtils.py
bertsenclu-0.1.8.dist-info/LICENSE
bertsenclu-0.1.8.dist-info/METADATA
bertsenclu-0.1.8.dist-info/WHEEL
bertsenclu-0.1.8.dist-info/top_level.txt
bertsenclu-0.1.8.dist-info/RECORD
