Metadata-Version: 2.1
Name: bertsenclu
Version: 0.1.8
Summary: (Bert-)SenClu is a topic modeling technique that leverages sentence transformers to compute topic models.
Home-page: https://github.com/JohnTailor/BertSenClu
Author: Johannes Schneider
Author-email: vollkoff@gmail.com
License: LICENSE
Project-URL: Source Code, https://github.com/JohnTailor/BertSenClu/
Project-URL: Issue Tracker, https://github.com/JohnTailor/BertSenClu/issues
Keywords: nlp bert topic modeling sentence embeddings
Classifier: Programming Language :: Python
Classifier: Intended Audience :: Science/Research
Classifier: Intended Audience :: Developers
Classifier: Topic :: Scientific/Engineering :: Artificial Intelligence
Classifier: License :: OSI Approved :: MIT License
Classifier: Topic :: Scientific/Engineering
Classifier: Operating System :: Microsoft :: Windows
Classifier: Operating System :: POSIX
Classifier: Operating System :: Unix
Classifier: Operating System :: MacOS
Classifier: Programming Language :: Python :: 3.7
Classifier: Programming Language :: Python :: 3.9
Classifier: Programming Language :: Python :: 3.8
Requires-Python: >=3.7
License-File: LICENSE
Requires-Dist: numpy (>=1.20.0)
Requires-Dist: pandas (>=1.1.5)
Requires-Dist: scikit-learn (>=0.22.2.post1)
Requires-Dist: sentence-transformers (>=0.4.1)
Requires-Dist: streamlit (>=1.17.0)
Requires-Dist: pysbd (>=0.3.4)
Requires-Dist: torch (>=1.11.0)
